{"abstract":[{"text":"Performs animations with a decaying acceleration.","type":"text"}],"hierarchy":{"paths":[["doc:\/\/Anima\/documentation\/Anima","doc:\/\/Anima\/documentation\/Anima\/Anima"]]},"seeAlsoSections":[{"generated":true,"title":"Animations","identifiers":["doc:\/\/Anima\/documentation\/Anima\/Anima\/animate(withEasing:duration:delay:options:animations:completion:)","doc:\/\/Anima\/documentation\/Anima\/Anima\/animate(withSpring:gestureVelocity:delay:options:animations:completion:)"]}],"schemaVersion":{"major":0,"minor":3,"patch":0},"kind":"symbol","identifier":{"interfaceLanguage":"swift","url":"doc:\/\/Anima\/documentation\/Anima\/Anima\/animate(withDecay:decelerationRate:delay:options:animations:completion:)"},"primaryContentSections":[{"kind":"declarations","declarations":[{"tokens":[{"text":"static","kind":"keyword"},{"kind":"text","text":" "},{"kind":"keyword","text":"func"},{"text":" ","kind":"text"},{"text":"animate","kind":"identifier"},{"text":"(","kind":"text"},{"kind":"externalParam","text":"withDecay"},{"text":" ","kind":"text"},{"kind":"internalParam","text":"mode"},{"text":": ","kind":"text"},{"preciseIdentifier":"s:5AnimaAAC18DecayAnimationModeO","kind":"typeIdentifier","text":"DecayAnimationMode","identifier":"doc:\/\/Anima\/documentation\/Anima\/Anima\/DecayAnimationMode"},{"kind":"text","text":", "},{"text":"decelerationRate","kind":"externalParam"},{"text":": ","kind":"text"},{"text":"Double","kind":"typeIdentifier","preciseIdentifier":"s:Sd"},{"text":" = DecayFunction.ScrollViewDecelerationRate, ","kind":"text"},{"text":"delay","kind":"externalParam"},{"text":": ","kind":"text"},{"preciseIdentifier":"c:@T@NSTimeInterval","text":"TimeInterval","kind":"typeIdentifier"},{"text":" = 0, ","kind":"text"},{"kind":"externalParam","text":"options"},{"text":": ","kind":"text"},{"preciseIdentifier":"s:5AnimaAAC16AnimationOptionsV","text":"AnimationOptions","kind":"typeIdentifier","identifier":"doc:\/\/Anima\/documentation\/Anima\/Anima\/AnimationOptions"},{"text":" = [], ","kind":"text"},{"text":"animations","kind":"externalParam"},{"text":": () -> ","kind":"text"},{"preciseIdentifier":"s:s4Voida","text":"Void","kind":"typeIdentifier"},{"kind":"text","text":", "},{"text":"completion","kind":"externalParam"},{"text":": ((","kind":"text"},{"kind":"externalParam","text":"_"},{"text":" ","kind":"text"},{"text":"finished","kind":"internalParam"},{"text":": ","kind":"text"},{"text":"Bool","preciseIdentifier":"s:Sb","kind":"typeIdentifier"},{"text":", ","kind":"text"},{"kind":"externalParam","text":"_"},{"kind":"text","text":" "},{"text":"retargeted","kind":"internalParam"},{"text":": ","kind":"text"},{"preciseIdentifier":"s:Sb","kind":"typeIdentifier","text":"Bool"},{"text":") -> ","kind":"text"},{"kind":"typeIdentifier","preciseIdentifier":"s:s4Voida","text":"Void"},{"kind":"text","text":")? = nil)"}],"languages":["swift"],"platforms":["macOS"]}]},{"parameters":[{"name":"mode","content":[{"inlineContent":[{"type":"text","text":"The mode how the animation should animate properties:"}],"type":"paragraph"},{"items":[{"content":[{"type":"paragraph","inlineContent":[{"identifier":"doc:\/\/Anima\/documentation\/Anima\/Anima\/DecayAnimationMode\/value","type":"reference","isActive":true},{"text":" will animate properties to the applied values with a decaying acceleration.","type":"text"}]}]},{"content":[{"inlineContent":[{"type":"reference","isActive":true,"identifier":"doc:\/\/Anima\/documentation\/Anima\/Anima\/DecayAnimationMode\/velocity"},{"type":"text","text":" will increase or decrease properties depending on the values applied and will slow to a stop.  This essentially provides the same “decaying” that "},{"type":"codeVoice","code":"UIScrollView"},{"text":" does when you drag and let go. The animation is seeded with velocity, and that velocity decays over time.","type":"text"}],"type":"paragraph"}]}],"type":"unorderedList"}]},{"name":"decelerationRate","content":[{"inlineContent":[{"type":"text","text":"The rate at which the animation decelerates over time. The default value decelerates like scrollviews."}],"type":"paragraph"}]},{"content":[{"type":"paragraph","inlineContent":[{"text":"An optional delay, in seconds, after which to start the animation.","type":"text"}]}],"name":"delay"},{"content":[{"type":"paragraph","inlineContent":[{"type":"text","text":"The options to apply to the animations. For a list of options, see "},{"type":"reference","isActive":true,"identifier":"doc:\/\/Anima\/documentation\/Anima\/Anima\/AnimationOptions"},{"text":". The default value is ","type":"text"},{"type":"codeVoice","code":"[]"},{"type":"text","text":"."}]}],"name":"options"},{"content":[{"inlineContent":[{"type":"text","text":"A block containing the changes to your objects’ animatable properties. Note that for animations to work correctly, you must set values on the object’s "},{"isActive":true,"type":"reference","identifier":"doc:\/\/Anima\/documentation\/Anima\/AnimatablePropertyProvider\/animator-94wn0"},{"type":"text","text":", not just the object itself."}],"type":"paragraph"}],"name":"animations"},{"name":"completion","content":[{"inlineContent":[{"type":"text","text":"An optional block to be executed when the specified animations have either finished or retargeted to a new value."}],"type":"paragraph"}]}],"kind":"parameters"},{"kind":"content","content":[{"anchor":"discussion","level":2,"text":"Discussion","type":"heading"},{"inlineContent":[{"type":"text","text":"There are two decay modes:"}],"type":"paragraph"},{"type":"unorderedList","items":[{"content":[{"inlineContent":[{"type":"strong","inlineContent":[{"text":"value:","type":"text"}]},{"type":"text","text":" The properties will animate to your values with a decelerating acceleration."}],"type":"paragraph"}]},{"content":[{"inlineContent":[{"type":"strong","inlineContent":[{"type":"text","text":"velocity:"}]},{"type":"text","text":":  The properties will increase or decrease depending on the values applied and will slow to a stop.  This essentially provides the same “decaying” that "},{"code":"UIScrollView","type":"codeVoice"},{"type":"text","text":" does when you drag and let go. The animation is seeded with velocity, and that velocity decays over time."}],"type":"paragraph"}]}]},{"inlineContent":[{"type":"text","text":"Example usage:"}],"type":"paragraph"},{"syntax":"swift","type":"codeListing","code":["\/\/ Value based decay animation","Anima.animate(withDecay: .value, animations: {","   \/\/ Animates the view's origin to the point with a decelerating rate.","   view.animator.frame.origin = CGPoint(x: 50, y: 50)","})","","\/\/ Velocity based decay animation","Anima.animate(withDecay: .velocity, animations: {","   \/\/ Increaes the view's origin by 50 points with a decelerating rate.","   view.animator.frame.origin = CGPoint(x: 50, y: 50)","})"]},{"style":"note","type":"aside","content":[{"type":"paragraph","inlineContent":[{"type":"text","text":"For animations to work correctly, you must set values on the objects’s "},{"isActive":true,"identifier":"doc:\/\/Anima\/documentation\/Anima\/AnimatablePropertyProvider\/animator-94wn0","type":"reference"},{"text":", not just the object itself. For example, to animate a view’s alpha, use ","type":"text"},{"code":"myView.animator.alpha = 1.0","type":"codeVoice"},{"text":" instead of ","type":"text"},{"type":"codeVoice","code":"myView.alpha = 1.0"},{"type":"text","text":". For a list of all objects that provide animatable properties check "},{"type":"reference","isActive":true,"identifier":"doc:\/\/Anima\/documentation\/Anima\/Anima"},{"text":".","type":"text"}]}],"name":"Note"}]}],"variants":[{"paths":["\/documentation\/anima\/anima\/animate(withdecay:decelerationrate:delay:options:animations:completion:)"],"traits":[{"interfaceLanguage":"swift"}]}],"sections":[],"metadata":{"externalID":"s:5AnimaAAC7animate9withDecay16decelerationRate5delay7options10animations10completionyAB0D13AnimationModeO_S2dAB0K7OptionsVyyXEySb_SbtcSgtFZ","role":"symbol","roleHeading":"Type Method","title":"animate(withDecay:decelerationRate:delay:options:animations:completion:)","modules":[{"name":"Anima"}],"fragments":[{"kind":"keyword","text":"static"},{"text":" ","kind":"text"},{"text":"func","kind":"keyword"},{"text":" ","kind":"text"},{"text":"animate","kind":"identifier"},{"kind":"text","text":"("},{"text":"withDecay","kind":"externalParam"},{"text":": ","kind":"text"},{"kind":"typeIdentifier","preciseIdentifier":"s:5AnimaAAC18DecayAnimationModeO","text":"DecayAnimationMode"},{"text":", ","kind":"text"},{"text":"decelerationRate","kind":"externalParam"},{"kind":"text","text":": "},{"text":"Double","kind":"typeIdentifier","preciseIdentifier":"s:Sd"},{"text":", ","kind":"text"},{"kind":"externalParam","text":"delay"},{"text":": ","kind":"text"},{"text":"TimeInterval","kind":"typeIdentifier","preciseIdentifier":"c:@T@NSTimeInterval"},{"text":", ","kind":"text"},{"kind":"externalParam","text":"options"},{"text":": ","kind":"text"},{"preciseIdentifier":"s:5AnimaAAC16AnimationOptionsV","text":"AnimationOptions","kind":"typeIdentifier"},{"text":", ","kind":"text"},{"text":"animations","kind":"externalParam"},{"kind":"text","text":": () -> "},{"kind":"typeIdentifier","text":"Void","preciseIdentifier":"s:s4Voida"},{"text":", ","kind":"text"},{"text":"completion","kind":"externalParam"},{"text":": ((","kind":"text"},{"kind":"externalParam","text":"_"},{"text":" ","kind":"text"},{"kind":"internalParam","text":"finished"},{"text":": ","kind":"text"},{"kind":"typeIdentifier","text":"Bool","preciseIdentifier":"s:Sb"},{"text":", ","kind":"text"},{"kind":"externalParam","text":"_"},{"text":" ","kind":"text"},{"text":"retargeted","kind":"internalParam"},{"text":": ","kind":"text"},{"text":"Bool","kind":"typeIdentifier","preciseIdentifier":"s:Sb"},{"kind":"text","text":") -> "},{"kind":"typeIdentifier","preciseIdentifier":"s:s4Voida","text":"Void"},{"kind":"text","text":")?)"}],"symbolKind":"method"},"references":{"doc://Anima/documentation/Anima/AnimatablePropertyProvider/animator-94wn0":{"url":"\/documentation\/anima\/animatablepropertyprovider\/animator-94wn0","defaultImplementations":3,"title":"animator","type":"topic","required":true,"abstract":[{"text":"It provides all animatable properties of the object. To animate them change their value inside an ","type":"text"},{"type":"reference","identifier":"doc:\/\/Anima\/documentation\/Anima\/Anima","isActive":true},{"text":" animation block.","type":"text"}],"role":"symbol","identifier":"doc:\/\/Anima\/documentation\/Anima\/AnimatablePropertyProvider\/animator-94wn0","fragments":[{"kind":"keyword","text":"var"},{"kind":"text","text":" "},{"text":"animator","kind":"identifier"},{"text":": ","kind":"text"},{"kind":"typeIdentifier","preciseIdentifier":"s:5Anima16PropertyAnimatorC","text":"PropertyAnimator"},{"text":"<","kind":"text"},{"preciseIdentifier":"s:5Anima26AnimatablePropertyProviderP0D0Qa","kind":"typeIdentifier","text":"Provider"},{"text":">","kind":"text"}],"kind":"symbol"},"doc://Anima/documentation/Anima/Anima":{"role":"symbol","url":"\/documentation\/anima\/anima","identifier":"doc:\/\/Anima\/documentation\/Anima\/Anima","fragments":[{"kind":"keyword","text":"class"},{"kind":"text","text":" "},{"text":"Anima","kind":"identifier"}],"title":"Anima","kind":"symbol","abstract":[{"type":"text","text":"Performs animations on animatable properties of objects conforming to "},{"identifier":"doc:\/\/Anima\/documentation\/Anima\/AnimatablePropertyProvider","isActive":true,"type":"reference"},{"text":".","type":"text"}],"type":"topic","navigatorTitle":[{"kind":"identifier","text":"Anima"}]},"doc://Anima/documentation/Anima/Anima/DecayAnimationMode/value":{"role":"symbol","abstract":[{"type":"text","text":"The animated properties will animate to the applied values  with a decelerating rate."}],"type":"topic","url":"\/documentation\/anima\/anima\/decayanimationmode\/value","fragments":[{"kind":"keyword","text":"case"},{"kind":"text","text":" "},{"text":"value","kind":"identifier"}],"kind":"symbol","identifier":"doc:\/\/Anima\/documentation\/Anima\/Anima\/DecayAnimationMode\/value","title":"Anima.DecayAnimationMode.value"},"doc://Anima/documentation/Anima/Spring":{"kind":"symbol","url":"\/documentation\/anima\/spring","title":"Spring","abstract":[{"type":"text","text":"A representation of a spring’s motion."}],"fragments":[{"text":"struct","kind":"keyword"},{"text":" ","kind":"text"},{"text":"Spring","kind":"identifier"}],"identifier":"doc:\/\/Anima\/documentation\/Anima\/Spring","navigatorTitle":[{"kind":"identifier","text":"Spring"}],"type":"topic","role":"symbol"},"doc://Anima/documentation/Anima/Anima/animate(withSpring:gestureVelocity:delay:options:animations:completion:)":{"role":"symbol","abstract":[{"type":"text","text":"Performs spring animations based on the specified "},{"identifier":"doc:\/\/Anima\/documentation\/Anima\/Spring","type":"reference","isActive":true},{"text":".","type":"text"}],"type":"topic","url":"\/documentation\/anima\/anima\/animate(withspring:gesturevelocity:delay:options:animations:completion:)","fragments":[{"kind":"keyword","text":"static"},{"text":" ","kind":"text"},{"kind":"keyword","text":"func"},{"text":" ","kind":"text"},{"kind":"identifier","text":"animate"},{"text":"(","kind":"text"},{"text":"withSpring","kind":"externalParam"},{"kind":"text","text":": "},{"kind":"typeIdentifier","preciseIdentifier":"s:5Anima6SpringV","text":"Spring"},{"kind":"text","text":", "},{"kind":"externalParam","text":"gestureVelocity"},{"kind":"text","text":": "},{"text":"CGPoint","preciseIdentifier":"c:@S@CGPoint","kind":"typeIdentifier"},{"text":"?, ","kind":"text"},{"kind":"externalParam","text":"delay"},{"text":": ","kind":"text"},{"text":"TimeInterval","kind":"typeIdentifier","preciseIdentifier":"c:@T@NSTimeInterval"},{"text":", ","kind":"text"},{"text":"options","kind":"externalParam"},{"kind":"text","text":": "},{"preciseIdentifier":"s:5AnimaAAC16AnimationOptionsV","kind":"typeIdentifier","text":"AnimationOptions"},{"kind":"text","text":", "},{"text":"animations","kind":"externalParam"},{"kind":"text","text":": () -> "},{"text":"Void","kind":"typeIdentifier","preciseIdentifier":"s:s4Voida"},{"text":", ","kind":"text"},{"text":"completion","kind":"externalParam"},{"kind":"text","text":": (("},{"kind":"externalParam","text":"_"},{"text":" ","kind":"text"},{"text":"finished","kind":"internalParam"},{"text":": ","kind":"text"},{"text":"Bool","kind":"typeIdentifier","preciseIdentifier":"s:Sb"},{"text":", ","kind":"text"},{"text":"_","kind":"externalParam"},{"text":" ","kind":"text"},{"text":"retargeted","kind":"internalParam"},{"text":": ","kind":"text"},{"kind":"typeIdentifier","text":"Bool","preciseIdentifier":"s:Sb"},{"kind":"text","text":") -> "},{"preciseIdentifier":"s:s4Voida","kind":"typeIdentifier","text":"Void"},{"kind":"text","text":")?)"}],"kind":"symbol","identifier":"doc:\/\/Anima\/documentation\/Anima\/Anima\/animate(withSpring:gestureVelocity:delay:options:animations:completion:)","title":"animate(withSpring:gestureVelocity:delay:options:animations:completion:)"},"doc://Anima/documentation/Anima/Anima/AnimationOptions":{"role":"symbol","url":"\/documentation\/anima\/anima\/animationoptions","identifier":"doc:\/\/Anima\/documentation\/Anima\/Anima\/AnimationOptions","fragments":[{"kind":"keyword","text":"struct"},{"kind":"text","text":" "},{"text":"AnimationOptions","kind":"identifier"}],"kind":"symbol","type":"topic","title":"Anima.AnimationOptions","abstract":[{"text":"Options for animations.","type":"text"}],"navigatorTitle":[{"kind":"identifier","text":"AnimationOptions"}]},"doc://Anima/documentation/Anima/Anima/DecayAnimationMode":{"role":"symbol","abstract":[{"type":"text","text":"The mode how "},{"identifier":"doc:\/\/Anima\/documentation\/Anima\/Anima","isActive":true,"type":"reference"},{"type":"text","text":" should animate properties with a decaying animation."}],"type":"topic","url":"\/documentation\/anima\/anima\/decayanimationmode","fragments":[{"kind":"keyword","text":"enum"},{"kind":"text","text":" "},{"text":"DecayAnimationMode","kind":"identifier"}],"navigatorTitle":[{"text":"DecayAnimationMode","kind":"identifier"}],"kind":"symbol","identifier":"doc:\/\/Anima\/documentation\/Anima\/Anima\/DecayAnimationMode","title":"Anima.DecayAnimationMode"},"doc://Anima/documentation/Anima/Anima/animate(withEasing:duration:delay:options:animations:completion:)":{"kind":"symbol","role":"symbol","type":"topic","abstract":[{"text":"Performs easing animations based on the specified ","type":"text"},{"isActive":true,"type":"reference","identifier":"doc:\/\/Anima\/documentation\/Anima\/TimingFunction"},{"text":".","type":"text"}],"title":"animate(withEasing:duration:delay:options:animations:completion:)","url":"\/documentation\/anima\/anima\/animate(witheasing:duration:delay:options:animations:completion:)","fragments":[{"text":"static","kind":"keyword"},{"text":" ","kind":"text"},{"text":"func","kind":"keyword"},{"kind":"text","text":" "},{"kind":"identifier","text":"animate"},{"kind":"text","text":"("},{"text":"withEasing","kind":"externalParam"},{"kind":"text","text":": "},{"preciseIdentifier":"s:5Anima14TimingFunctionO","text":"TimingFunction","kind":"typeIdentifier"},{"kind":"text","text":", "},{"kind":"externalParam","text":"duration"},{"text":": ","kind":"text"},{"text":"TimeInterval","kind":"typeIdentifier","preciseIdentifier":"c:@T@NSTimeInterval"},{"kind":"text","text":", "},{"text":"delay","kind":"externalParam"},{"text":": ","kind":"text"},{"preciseIdentifier":"c:@T@NSTimeInterval","text":"TimeInterval","kind":"typeIdentifier"},{"text":", ","kind":"text"},{"text":"options","kind":"externalParam"},{"text":": ","kind":"text"},{"kind":"typeIdentifier","text":"AnimationOptions","preciseIdentifier":"s:5AnimaAAC16AnimationOptionsV"},{"text":", ","kind":"text"},{"kind":"externalParam","text":"animations"},{"kind":"text","text":": () -> "},{"preciseIdentifier":"s:s4Voida","text":"Void","kind":"typeIdentifier"},{"text":", ","kind":"text"},{"kind":"externalParam","text":"completion"},{"text":": ((","kind":"text"},{"kind":"externalParam","text":"_"},{"kind":"text","text":" "},{"text":"finished","kind":"internalParam"},{"kind":"text","text":": "},{"kind":"typeIdentifier","text":"Bool","preciseIdentifier":"s:Sb"},{"kind":"text","text":", "},{"text":"_","kind":"externalParam"},{"text":" ","kind":"text"},{"text":"retargeted","kind":"internalParam"},{"text":": ","kind":"text"},{"kind":"typeIdentifier","text":"Bool","preciseIdentifier":"s:Sb"},{"text":") -> ","kind":"text"},{"text":"Void","kind":"typeIdentifier","preciseIdentifier":"s:s4Voida"},{"text":")?)","kind":"text"}],"identifier":"doc:\/\/Anima\/documentation\/Anima\/Anima\/animate(withEasing:duration:delay:options:animations:completion:)"},"doc://Anima/documentation/Anima/Anima/animate(withDecay:decelerationRate:delay:options:animations:completion:)":{"role":"symbol","abstract":[{"text":"Performs animations with a decaying acceleration.","type":"text"}],"type":"topic","url":"\/documentation\/anima\/anima\/animate(withdecay:decelerationrate:delay:options:animations:completion:)","fragments":[{"kind":"keyword","text":"static"},{"kind":"text","text":" "},{"text":"func","kind":"keyword"},{"kind":"text","text":" "},{"text":"animate","kind":"identifier"},{"text":"(","kind":"text"},{"kind":"externalParam","text":"withDecay"},{"kind":"text","text":": "},{"text":"DecayAnimationMode","kind":"typeIdentifier","preciseIdentifier":"s:5AnimaAAC18DecayAnimationModeO"},{"kind":"text","text":", "},{"text":"decelerationRate","kind":"externalParam"},{"text":": ","kind":"text"},{"text":"Double","kind":"typeIdentifier","preciseIdentifier":"s:Sd"},{"text":", ","kind":"text"},{"text":"delay","kind":"externalParam"},{"text":": ","kind":"text"},{"preciseIdentifier":"c:@T@NSTimeInterval","kind":"typeIdentifier","text":"TimeInterval"},{"text":", ","kind":"text"},{"text":"options","kind":"externalParam"},{"kind":"text","text":": "},{"preciseIdentifier":"s:5AnimaAAC16AnimationOptionsV","kind":"typeIdentifier","text":"AnimationOptions"},{"text":", ","kind":"text"},{"kind":"externalParam","text":"animations"},{"text":": () -> ","kind":"text"},{"kind":"typeIdentifier","text":"Void","preciseIdentifier":"s:s4Voida"},{"kind":"text","text":", "},{"text":"completion","kind":"externalParam"},{"text":": ((","kind":"text"},{"text":"_","kind":"externalParam"},{"text":" ","kind":"text"},{"kind":"internalParam","text":"finished"},{"text":": ","kind":"text"},{"text":"Bool","preciseIdentifier":"s:Sb","kind":"typeIdentifier"},{"text":", ","kind":"text"},{"kind":"externalParam","text":"_"},{"text":" ","kind":"text"},{"kind":"internalParam","text":"retargeted"},{"text":": ","kind":"text"},{"kind":"typeIdentifier","preciseIdentifier":"s:Sb","text":"Bool"},{"text":") -> ","kind":"text"},{"kind":"typeIdentifier","preciseIdentifier":"s:s4Voida","text":"Void"},{"text":")?)","kind":"text"}],"kind":"symbol","identifier":"doc:\/\/Anima\/documentation\/Anima\/Anima\/animate(withDecay:decelerationRate:delay:options:animations:completion:)","title":"animate(withDecay:decelerationRate:delay:options:animations:completion:)"},"doc://Anima/documentation/Anima/AnimatablePropertyProvider":{"url":"\/documentation\/anima\/animatablepropertyprovider","role":"symbol","fragments":[{"text":"protocol","kind":"keyword"},{"text":" ","kind":"text"},{"text":"AnimatablePropertyProvider","kind":"identifier"}],"title":"AnimatablePropertyProvider","kind":"symbol","navigatorTitle":[{"text":"AnimatablePropertyProvider","kind":"identifier"}],"abstract":[{"text":"An object that provides animatable properties that can be accessed via it’s ","type":"text"},{"isActive":true,"identifier":"doc:\/\/Anima\/documentation\/Anima\/AnimatablePropertyProvider\/animator-94wn0","type":"reference"},{"text":".","type":"text"}],"type":"topic","identifier":"doc:\/\/Anima\/documentation\/Anima\/AnimatablePropertyProvider"},"doc://Anima/documentation/Anima/Anima/DecayAnimationMode/velocity":{"role":"symbol","abstract":[{"type":"text","text":"The value of animated properties will increase or decrease (depending on the values applied) with a decelerating rate.  This essentially provides the same “decaying” that "},{"type":"codeVoice","code":"UIScrollView"},{"type":"text","text":" does when you drag and let go. The animation is seeded with velocity, and that velocity decays over time."}],"type":"topic","url":"\/documentation\/anima\/anima\/decayanimationmode\/velocity","fragments":[{"kind":"keyword","text":"case"},{"kind":"text","text":" "},{"text":"velocity","kind":"identifier"}],"kind":"symbol","identifier":"doc:\/\/Anima\/documentation\/Anima\/Anima\/DecayAnimationMode\/velocity","title":"Anima.DecayAnimationMode.velocity"},"doc://Anima/documentation/Anima/TimingFunction":{"role":"symbol","fragments":[{"text":"enum","kind":"keyword"},{"text":" ","kind":"text"},{"text":"TimingFunction","kind":"identifier"}],"navigatorTitle":[{"text":"TimingFunction","kind":"identifier"}],"title":"TimingFunction","url":"\/documentation\/anima\/timingfunction","type":"topic","abstract":[{"type":"text","text":"The timing function maps an input time normalized to the range "},{"type":"codeVoice","code":"[0,1]"},{"text":" to an output time also in the range ","type":"text"},{"code":"[0,1]","type":"codeVoice"},{"text":". It’s used to define the pacing of an animation as a timing curve.","type":"text"}],"identifier":"doc:\/\/Anima\/documentation\/Anima\/TimingFunction","kind":"symbol"},"doc://Anima/documentation/Anima":{"kind":"symbol","type":"topic","url":"\/documentation\/anima","identifier":"doc:\/\/Anima\/documentation\/Anima","title":"Anima","role":"collection","abstract":[{"type":"text","text":"Anima is an animation framework for iOS, tvOS, and macOS. It can animate properties using spring, easing and decay animations."}]}}}